h_testkit/__init__.py
h_testkit/factoryboy.py
h_testkit/pytest_plugin.py
h_testkit-1.0.1.dist-info/LICENSE
h_testkit-1.0.1.dist-info/METADATA
h_testkit-1.0.1.dist-info/WHEEL
h_testkit-1.0.1.dist-info/entry_points.txt
h_testkit-1.0.1.dist-info/top_level.txt
h_testkit-1.0.1.dist-info/RECORD
