Metadata-Version: 2.1
Name: h-testkit
Version: 1.0.1
Summary: A collection of pytest fixtures and other shared code for use in Python tests.
Home-page: https://github.com/hypothesis/h-testkit
Project-URL: Bug Tracker, https://github.com/hypothesis/h-testkit/issues
Project-URL: Changelog, https://github.com/hypothesis/h-testkit/releases
Classifier: Framework :: Pytest
Requires-Python: >=3.8
License-File: LICENSE
